cfsm_bisimulation/__init__.py
cfsm_bisimulation/libs/tools.py
cfsm_bisimulation/libs/z3_renamer.py
cfsm_bisimulation/libs/symmetrical_collections/dict.py
cfsm_bisimulation/libs/symmetrical_collections/list.py
cfsm_bisimulation/libs/symmetrical_collections/symmetical.py
cfsm_bisimulation/libs/symmetrical_collections/symmetry_mode.py
cfsm_bisimulation/models/__init__.py
cfsm_bisimulation/models/assertable_finite_state_machines/afsm.py
cfsm_bisimulation/models/assertable_finite_state_machines/assertable_label.py
cfsm_bisimulation/models/assertable_finite_state_machines/assertion.py
cfsm_bisimulation/models/assertable_finite_state_machines/state.py
cfsm_bisimulation/models/assertable_finite_state_machines/transition.py
cfsm_bisimulation/models/communicating_system/action.py
cfsm_bisimulation/models/communicating_system/action_parser.py
cfsm_bisimulation/models/communicating_system/cfsm.py
cfsm_bisimulation/models/communicating_system/factories/match_manager_factory.py
cfsm_bisimulation/models/communicating_system/factories/matcher_factory.py
cfsm_bisimulation/models/communicating_system/matchers/action_matcher.py
cfsm_bisimulation/models/communicating_system/matchers/decider.py
cfsm_bisimulation/models/communicating_system/matchers/decision.py
cfsm_bisimulation/models/communicating_system/matchers/matcher.py
cfsm_bisimulation/models/communicating_system/matchers/message_matcher.py
cfsm_bisimulation/models/communicating_system/matchers/no_candidate_match_exception.py
cfsm_bisimulation/models/communicating_system/matchers/participant_matcher.py
cfsm_bisimulation/models/communicating_system/matchers/variable_matcher.py
cfsm_bisimulation/models/communicating_system/matches/match_manager.py
cfsm_bisimulation/models/communicating_system/matches/match_with_candidates_manager.py
cfsm_bisimulation/models/communicating_system/matches/message_match_manager.py
cfsm_bisimulation/models/stratified_bisimulation_strategies/initial_relation_builder.py
cfsm_bisimulation-2.1.0.dist-info/licenses/LICENSE.txt
cfsm_bisimulation-2.1.0.dist-info/METADATA
cfsm_bisimulation-2.1.0.dist-info/WHEEL
cfsm_bisimulation-2.1.0.dist-info/top_level.txt
cfsm_bisimulation-2.1.0.dist-info/RECORD
