Metadata-Version: 2.4
Name: cfsm-bisimulation
Version: 2.1.0
Summary: A bisiumlation data-aware algorithm for Communicating Finite State Machines with edge assertions (knowledge as a-CFSM)
Author-email: Diego Senarruzza <diegosenarruzza@gmail.com>
License: MIT License
Project-URL: Homepage, https://github.com/diegosenarruzza/bisimulation
Project-URL: Bug Reports, https://github.com/diegosenarruzza/bisimulation/issues
Project-URL: Source, https://github.com/diegosenarruzza/bisimulation
Keywords: bisimulation,cfsm,automaton
Classifier: Development Status :: 4 - Beta
Classifier: License :: OSI Approved :: MIT License
Classifier: Operating System :: OS Independent
Classifier: Programming Language :: Python :: 3
Requires-Python: >=3.7
License-File: LICENSE.txt
Dynamic: license-file
